{"bodyType":"fit","bgColor":"#cccccc","version":"0.0.1","layers":[{"part":"torso","index":0,"shading":7,"base":"#333333","outline":"#cccccc"},{"part":"pants","index":13,"shading":0,"pattern":0,"resizeX":0.9299999999999999,"resizeY":1.1600000000000001,"base":"#333333","outline":"#cccccc"},{"part":"pants","index":12,"shading":9,"resizeX":1.04,"resizeY":1.1600000000000001,"base":"#333333","outline":"#cccccc","detail":"#666666"},{"part":"belt","index":5,"shading":0,"resizeX":1.01,"base":"#333333","outline":"#999999"},{"part":"belt","index":6,"shading":0,"resizeX":1.01,"base":"#333333","outline":"#999999"},{"part":"belt","index":3,"shading":0,"resizeX":1.01,"base":"#333333","outline":"#999999"},{"part":"belt","index":42,"shading":12,"resizeX":1.01,"base":"#999999","detail":"#666666"},{"part":"belt","index":1,"shading":0,"resizeX":1.03,"detail":"#333333","base":"#333333","outline":"#999999"},{"part":"hat","index":62,"shading":13,"resizeY":0.5299999999999996,"resizeX":0.5299999999999996,"moveY":93,"base":"#333333","detail":"#333333"},{"part":"hat","index":63,"shading":13,"resizeY":0.5299999999999996,"resizeX":0.5299999999999996,"moveY":93,"base":"#999999"},{"part":"arm","index":4,"shading":0,"base":"#6633ff","detail":"#333333"},{"part":"arm","index":4,"shading":0,"flip":true,"base":"#6633ff","detail":"#333333"},{"part":"shirt","index":12,"shading":7,"base":"#333333","outline":"#cccccc"},{"part":"collar","index":14,"shading":0,"base":"#cc3300"},{"part":"chest","index":53,"shading":13,"base":"#cccccc","detail":"#999999"},{"part":"head","index":69,"shading":0,"resizeX":0.7499999999999998,"resizeY":0.8499999999999999,"base":"#6633ff"},{"part":"shirt","index":84,"shading":13,"base":"#999999"},{"part":"shirt","index":80,"shading":13,"base":"#999999"},{"part":"sholders","index":1,"shading":13,"base":"#999999"},{"part":"gauntlets","index":40,"shading":13,"resizeX":0.7799999999999998,"moveX":-13,"resizeY":1.1500000000000001,"moveY":-8,"base":"#999999","detail":"#cccccc"},{"part":"gauntlets","index":40,"shading":13,"resizeX":0.7799999999999998,"moveX":13,"resizeY":1.1500000000000001,"moveY":-8,"flip":true,"base":"#999999","detail":"#cccccc"},{"part":"eyes","index":3,"shading":0,"moveY":16,"detail":"#000000"}],"bodyScale":"lanky"}